jesse_rust-1.0.1.dist-info/METADATA
jesse_rust-1.0.1.dist-info/WHEEL
jesse_rust-1.0.1.dist-info/licenses/LICENSE
jesse_rust/__init__.py
jesse_rust/jesse_rust.cpython-313-x86_64-linux-gnu.so
jesse_rust-1.0.1.dist-info/RECORD
