Metadata-Version: 2.4
Name: jesse-rust
Version: 1.0.1
Classifier: Development Status :: 4 - Beta
Classifier: Intended Audience :: Developers
Classifier: Intended Audience :: Financial and Insurance Industry
Classifier: License :: OSI Approved :: MIT License
Classifier: Operating System :: OS Independent
Classifier: Programming Language :: Python :: 3
Classifier: Programming Language :: Python :: 3.10
Classifier: Programming Language :: Python :: 3.11
Classifier: Programming Language :: Python :: 3.12
Classifier: Programming Language :: Python :: 3.13
Classifier: Programming Language :: Python :: Implementation :: CPython
Classifier: Programming Language :: Rust
Classifier: Topic :: Office/Business :: Financial :: Investment
Classifier: Topic :: Scientific/Engineering :: Mathematics
Classifier: Topic :: Software Development :: Libraries :: Python Modules
Requires-Dist: numpy>=1.26.4
License-File: LICENSE
Summary: High-performance Rust-based technical indicators for Jesse trading framework
Keywords: trading,technical-analysis,indicators,rust,performance
Author-email: Saleh Mir <saleh@jesse.trade>
Maintainer-email: Saleh Mir <saleh@jesse.trade>
License: MIT
Requires-Python: >=3.10
Project-URL: Homepage, https://jesse.trade
Project-URL: Documentation, https://docs.jesse.trade
Project-URL: Repository, https://github.com/jesse-ai/jesse-rust
Project-URL: Bug Reports, https://github.com/jesse-ai/jesse-rust/issues
